scripts/__init__.py
scripts/translation.py
trajson-0.0.2.dist-info/METADATA
trajson-0.0.2.dist-info/WHEEL
trajson-0.0.2.dist-info/entry_points.txt
trajson-0.0.2.dist-info/top_level.txt
trajson-0.0.2.dist-info/RECORD
