Metadata-Version: 2.1
Name: trajson
Version: 0.0.2
Summary: Translate json files.
Home-page: UNKNOWN
Author: Ismael Traoré
Author-email: proximusexam@gmail.com
License: UNKNOWN
Platform: UNKNOWN
Classifier: Programming Language :: Python :: 3
Requires-Dist: Click
